cpd/__init__.py
cpd/cli.py
cpd/config.py
cpd/data/__init__.py
cpd/data/signatures.py
cpd/engine.py
cpd/http_client.py
cpd/logic/__init__.py
cpd/logic/baseline.py
cpd/logic/blind.py
cpd/logic/cache_guard.py
cpd/logic/cache_key_analyzer.py
cpd/logic/dom_analyzer.py
cpd/logic/exotic_poisoning.py
cpd/logic/filter.py
cpd/logic/mutator.py
cpd/logic/normalization.py
cpd/logic/poison.py
cpd/logic/probing.py
cpd/logic/smuggling.py
cpd/logic/validator.py
cpd/logic/waf_bypass.py
cpd/main.py
cpd/utils/__init__.py
cpd/utils/logger.py
cpd/utils/parser.py
cpd/utils/poc_generator.py
cpd/utils/reporter.py
cpd/utils/session.py
cpd_sec-0.9.0.dist-info/LICENSE
cpd_sec-0.9.0.dist-info/METADATA
cpd_sec-0.9.0.dist-info/WHEEL
cpd_sec-0.9.0.dist-info/entry_points.txt
cpd_sec-0.9.0.dist-info/RECORD
