Metadata-Version: 2.1
Name: cpd-sec
Version: 0.9.0
Summary: A high-concurrency CLI tool for detecting web cache poisoning vulnerabilities.
Home-page: https://github.com/kankburhan/cpd
Author: kankburhan
Author-email: kankburhan@gmail.com
Requires-Python: >=3.9,<4.0
Classifier: Programming Language :: Python :: 3
Classifier: Programming Language :: Python :: 3.9
Classifier: Programming Language :: Python :: 3.10
Classifier: Programming Language :: Python :: 3.11
Classifier: Programming Language :: Python :: 3.12
Requires-Dist: PyYAML (>=6.0.1,<7.0.0)
Requires-Dist: aiohttp (>=3.9.1,<4.0.0)
Requires-Dist: click (>=8.1.7,<9.0.0)
Requires-Dist: requests (>=2.31.0,<3.0.0)
Project-URL: Repository, https://github.com/kankburhan/cpd
